<?xml version="1.0" encoding="utf-8" ?>
<dwsync>
<file name="01.jpg" server="natalina-com-ua.1gb.ua//" local="131204300968102364" remote="131260342800000000" Dst="1" />
<file name="02.jpg" server="natalina-com-ua.1gb.ua//" local="131204300874527012" remote="131260342800000000" Dst="1" />
<file name="03.jpg" server="natalina-com-ua.1gb.ua//" local="131204301361934890" remote="131260342800000000" Dst="1" />
<file name="04.jpg" server="natalina-com-ua.1gb.ua//" local="131204300656634549" remote="131260342800000000" Dst="1" />
<file name="05.jpg" server="natalina-com-ua.1gb.ua//" local="131204300514336410" remote="131260342800000000" Dst="1" />
<file name="06.jpg" server="natalina-com-ua.1gb.ua//" local="131204300401249942" remote="131260342800000000" Dst="1" />
<file name="07.jpg" server="natalina-com-ua.1gb.ua//" local="131204300274952719" remote="131260342800000000" Dst="1" />
<file name="08.jpg" server="natalina-com-ua.1gb.ua//" local="131204300156175925" remote="131260342800000000" Dst="1" />
<file name="09.jpg" server="natalina-com-ua.1gb.ua//" local="131204300049309812" remote="131260342800000000" Dst="1" />
<file name="01.jpg" server="natalina-com-ua.1gb.ua//http/" local="131204300968102364" remote="131260345200000000" Dst="1" />
<file name="03.jpg" server="natalina-com-ua.1gb.ua//http/" local="131204301361934890" remote="131260345200000000" Dst="1" />
<file name="02.jpg" server="natalina-com-ua.1gb.ua//http/" local="131204300874527012" remote="131260345200000000" Dst="1" />
<file name="04.jpg" server="natalina-com-ua.1gb.ua//http/" local="131204300656634549" remote="131260345200000000" Dst="1" />
<file name="05.jpg" server="natalina-com-ua.1gb.ua//http/" local="131204300514336410" remote="131260345200000000" Dst="1" />
<file name="06.jpg" server="natalina-com-ua.1gb.ua//http/" local="131204300401249942" remote="131260345200000000" Dst="1" />
<file name="07.jpg" server="natalina-com-ua.1gb.ua//http/" local="131204300274952719" remote="131260345200000000" Dst="1" />
<file name="08.jpg" server="natalina-com-ua.1gb.ua//http/" local="131204300156175925" remote="131260345200000000" Dst="1" />
<file name="09.jpg" server="natalina-com-ua.1gb.ua//http/" local="131204300049309812" remote="131260345200000000" Dst="1" />
</dwsync>